<?xml version='1.0' encoding='utf-8'?>
<SBO_AccountsReceivableContainer><SBO_AccountsReceivable><SenderId>ID066</SenderId><CompanyCode>2800</CompanyCode><DocumentType>5R</DocumentType><DocumentDate>20220310</DocumentDate><PostingDate>20220310</PostingDate><Reference>28252623</Reference><HeaderText>1. erä</HeaderText><CurrencyCode>EUR</CurrencyCode><LineItem><AmountInDocumentCurrency>114,00</AmountInDocumentCurrency><LineText>1. erä</LineText><CustomerID>170375-018A</CustomerID><BaseLineDate>20230417</BaseLineDate><PaymentTerms>N073</PaymentTerms><ReferenceId>28252623</ReferenceId><InfoCustomerID>170375-018A</InfoCustomerID><InfoName1>Svensson</InfoName1><InfoName2>Sven</InfoName2><InfoAddress1>Jokutie 5 D</InfoAddress1><InfoCity>Helsinki</InfoCity><InfoPostalcode>24523</InfoPostalcode></LineItem><LineItem><TaxCode>4Z</TaxCode><AmountInDocumentCurrency>-114,00</AmountInDocumentCurrency><LineText>1. erä</LineText><GLAccount>350080</GLAccount><WBS_Element>282500477702302</WBS_Element></LineItem></SBO_AccountsReceivable></SBO_AccountsReceivableContainer>